FeilongDeAnzhuoNixiangJiaochengV10/README.md
FeilongDeAnzhuoNixiangJiaochengV10/__init__.py
FeilongDeAnzhuoNixiangJiaochengV10/__main__.py
FeilongDeAnzhuoNixiangJiaochengV10/file.epub
FeilongDeAnzhuoNixiangJiaochengV10/index.html
FeilongDeAnzhuoNixiangJiaochengV10/css/__init__.py
FeilongDeAnzhuoNixiangJiaochengV10/css/annotations.css
FeilongDeAnzhuoNixiangJiaochengV10/css/main.css
FeilongDeAnzhuoNixiangJiaochengV10/css/normalize.css
FeilongDeAnzhuoNixiangJiaochengV10/css/popup.css
FeilongDeAnzhuoNixiangJiaochengV10/font/__init__.py
FeilongDeAnzhuoNixiangJiaochengV10/font/fontello.eot
FeilongDeAnzhuoNixiangJiaochengV10/font/fontello.svg
FeilongDeAnzhuoNixiangJiaochengV10/font/fontello.ttf
FeilongDeAnzhuoNixiangJiaochengV10/font/fontello.woff
FeilongDeAnzhuoNixiangJiaochengV10/img/__init__.py
FeilongDeAnzhuoNixiangJiaochengV10/img/annotator-glyph-sprite.png
FeilongDeAnzhuoNixiangJiaochengV10/img/annotator-icon-sprite.png
FeilongDeAnzhuoNixiangJiaochengV10/img/apple-touch-icon.png
FeilongDeAnzhuoNixiangJiaochengV10/img/cancelfullscreen.png
FeilongDeAnzhuoNixiangJiaochengV10/img/close.png
FeilongDeAnzhuoNixiangJiaochengV10/img/fullscreen.png
FeilongDeAnzhuoNixiangJiaochengV10/img/loader.gif
FeilongDeAnzhuoNixiangJiaochengV10/img/menu-icon.png
FeilongDeAnzhuoNixiangJiaochengV10/img/save.png
FeilongDeAnzhuoNixiangJiaochengV10/img/saved.png
FeilongDeAnzhuoNixiangJiaochengV10/img/settings-s.png
FeilongDeAnzhuoNixiangJiaochengV10/img/settings.png
FeilongDeAnzhuoNixiangJiaochengV10/img/star.png
FeilongDeAnzhuoNixiangJiaochengV10/js/__init__.py
FeilongDeAnzhuoNixiangJiaochengV10/js/epub.js
FeilongDeAnzhuoNixiangJiaochengV10/js/epub.min.js
FeilongDeAnzhuoNixiangJiaochengV10/js/epub.min.map
FeilongDeAnzhuoNixiangJiaochengV10/js/hooks.min.js
FeilongDeAnzhuoNixiangJiaochengV10/js/hooks.min.map
FeilongDeAnzhuoNixiangJiaochengV10/js/reader.js
FeilongDeAnzhuoNixiangJiaochengV10/js/reader.js.map
FeilongDeAnzhuoNixiangJiaochengV10/js/reader.min.js
feilong_de_anzhuo_nixiang_jiaocheng_v1_0-2024.3.2.0.dist-info/METADATA
feilong_de_anzhuo_nixiang_jiaocheng_v1_0-2024.3.2.0.dist-info/WHEEL
feilong_de_anzhuo_nixiang_jiaocheng_v1_0-2024.3.2.0.dist-info/entry_points.txt
feilong_de_anzhuo_nixiang_jiaocheng_v1_0-2024.3.2.0.dist-info/top_level.txt
feilong_de_anzhuo_nixiang_jiaocheng_v1_0-2024.3.2.0.dist-info/RECORD
